{"path": "research/event_driven/lhb_amplitude_strategy.py", "language": "python", "kind": "research", "lines": 134, "bytes": 5419, "truncated": false, "content": "\"\"\"龙虎榜 振幅 volatility-spike drift — 预注册 (DSR trial #34, 2026-04-19).\n\n### 假设\nDSR #33 证明 \"seat 净买入 + 跌幅偏离 LHB\" contrarian 4/5 PASS.\n本策略 robustness check: 换 LHB category 到 **振幅 15%** — 同时包含上下震荡,\n不带方向 prior. Seat 净买入 若仍有 predictive power, 则 #33 alpha 不是\n仅 \"contrarian 跌幅\" 特异性, 而是 institutional informed-flow 通用信号.\n\n### Pre-registration spec (零 DoF)\n- 数据: _all_lhb_2018_2025.parquet\n- 事件筛选: 上榜原因 contain \"振幅\" (排除 涨幅/跌幅/换手率 for orthogonality)\n- 信号: 净买额占总成交比 > 0\n- 主板 only, monthly cross-section top 30% LONG\n- 窗口: T+1 ~ T+5 (与 #33 一致)\n- UNIT base: 1/30, gross cap: 1.0, 成本: 0.15% 单边\n\n### Admission gates (不变)\nann>15%, Sharpe>0.8, MDD>-30%, PSR>0.95, CI_low>0.5\n\n### DSR: 34 (robustness check, n_trials accumulator → 34)\n\"\"\"\nfrom __future__ import annotations\nimport logging\nfrom pathlib import Path\n\nimport numpy as np\nimport pandas as pd\n\nfrom utils.local_data_loader import load_adj_price_wide\nfrom utils.metrics import (\n    annualized_return, bootstrap_sharpe_ci, max_drawdown,\n    probabilistic_sharpe, sharpe_ratio,\n)\nfrom utils.risk_overlay import apply_gross_cap\n\nlogger = logging.getLogger(__name__)\n\nEVENTS = Path(\"data/raw/events/_all_lhb_2018_2025.parquet\")\nLISTING = pd.read_parquet(\"data/raw/listing_metadata.parquet\")\nMAIN_BOARD = set(LISTING[LISTING[\"board\"] == \"主板\"][\"symbol\"].tolist())\n\nHOLD_DAYS = 5\nPOST_OFFSET = 1\nTOP_PCT = 0.30\nTXN_ROUND_TRIP = 0.003\nUNIT_POS_WEIGHT = 1.0 / 30\n\n\ndef load_events(end: str) -> pd.DataFrame:\n    df = pd.read_parquet(EVENTS)\n    df[\"上榜日\"] = pd.to_datetime(df[\"上榜日\"], errors=\"coerce\")\n    df = df.dropna(subset=[\"上榜日\", \"代码\", \"净买额占总成交比\"])\n    df = df.rename(columns={\"代码\": \"symbol\", \"上榜日\": \"event_date\"})\n    df = df[df[\"上榜原因\"].str.contains(\"振幅\", na=False)]\n    df = df[df[\"symbol\"].isin(MAIN_BOARD)]\n    df[\"signal\"] = pd.to_numeric(df[\"净买额占总成交比\"], errors=\"coerce\")\n    df = df.dropna(subset=[\"signal\"])\n    df = df[df[\"signal\"] > 0]\n    df = df[df[\"event_date\"] <= pd.Timestamp(end)]\n    df = df.sort_values(\"signal\", ascending=False).drop_duplicates(\n        subset=[\"symbol\", \"event_date\"], keep=\"first\"\n    )\n    return df.reset_index(drop=True)\n\n\ndef build_weights(events, trading_days, unit_weight=UNIT_POS_WEIGHT):\n    symbols = sorted(events[\"symbol\"].unique())\n    W = pd.DataFrame(0.0, index=trading_days, columns=symbols, dtype=float)\n    td_arr = trading_days.values\n    events = events.copy()\n    events[\"month\"] = events[\"event_date\"].dt.to_period(\"M\")\n    n_pos = 0\n    for _, grp in events.groupby(\"month\", observed=True):\n        grp = grp.sort_values(\"signal\", ascending=False)\n        if len(grp) < 10:\n            continue\n        n_top = max(1, int(np.floor(len(grp) * TOP_PCT)))\n        for _, r in grp.iloc[:n_top].iterrows():\n            t = np.datetime64(r[\"event_date\"])\n            i_t = int(np.searchsorted(td_arr, t, side=\"left\"))\n            i_open = min(len(td_arr), i_t + POST_OFFSET)\n            i_close = min(len(td_arr), i_open + HOLD_DAYS)\n            if i_open >= i_close or r[\"symbol\"] not in W.columns:\n                continue\n            W.iloc[i_open:i_close, W.columns.get_loc(r[\"symbol\"])] += unit_weight\n            n_pos += 1\n    logger.info(f\"positions: {n_pos}\")\n    return W\n\n\ndef run_backtest(start=\"2018-01-01\", end=\"2025-12-31\"):\n    ev = load_events(end)\n    print(f\"events: {len(ev)}  {ev['event_date'].min().date()} ~ {ev['event_date'].max().date()}\")\n    universe = sorted(ev[\"symbol\"].dropna().unique().tolist())\n    prices = load_adj_price_wide(universe, start=start, end=end)\n    rets = prices.pct_change().where(lambda x: x.abs() < 0.25)\n\n    W = build_weights(ev, rets.index).reindex(columns=prices.columns).fillna(0)\n    W_cap = apply_gross_cap(W, cap=1.0)\n    w_exec = W_cap.shift(1)\n    daily_gross = (w_exec * rets).sum(axis=1)\n    turnover = w_exec.diff().abs().sum(axis=1).fillna(0)\n    net = (daily_gross - turnover * (TXN_ROUND_TRIP / 2)).loc[start:end].dropna()\n\n    ann = annualized_return(net); sr = sharpe_ratio(net); mdd = max_drawdown(net)\n    psr = probabilistic_sharpe(net, sr_benchmark=0.0)\n    boot = bootstrap_sharpe_ci(net, n_boot=2000)\n    gate = {\n        \"ann>15%\": ann > 0.15, \"sharpe>0.8\": sr > 0.8,\n        \"mdd>-30%\": mdd > -0.30, \"PSR>0.95\": psr > 0.95,\n        \"ci_low>0.5\": boot[\"ci_low\"] > 0.5,\n    }\n    n_pass = sum(gate.values())\n    print(f\"\\n=== DSR #34 LHB 振幅 volatility-spike drift ===\")\n    print(f\"  ann={ann:+.2%}  Sharpe={sr:.2f}  MDD={mdd:.2%}  PSR={psr:.3f}  CI=[{boot['ci_low']:.2f},{boot['ci_high']:.2f}]\")\n    for k, v in gate.items():\n        print(f\"    {'PASS' if v else 'FAIL'} {k}\")\n    print(f\"  {n_pass}/5\")\n    print(f\"  mean_gross={W_cap.abs().sum(axis=1).loc[start:end].mean():.3f}\")\n    return {\"returns\": net, \"n_pass\": n_pass, \"ann\": ann, \"sr\": sr, \"mdd\": mdd,\n            \"psr\": psr, \"ci_low\": boot[\"ci_low\"]}\n\n\ndef main():\n    logging.basicConfig(level=logging.WARNING)\n    result = run_backtest()\n    result[\"returns\"].rename(\"net_return\").to_frame().to_parquet(\n        \"research/event_driven/dsr34_lhb_amplitude_oos.parquet\"\n    )\n    print(f\"\\n保存: research/event_driven/dsr34_lhb_amplitude_oos.parquet\")\n\n\nif __name__ == \"__main__\":\n    main()\n"}