{"path": "dashboard/routers/risk.py", "language": "python", "kind": "risk", "lines": 23, "bytes": 507, "truncated": false, "content": "\"\"\"\nrouters/risk.py — 风险预警路由\n\nGET /api/risk/alerts → 当前持仓风险预警列表\n\"\"\"\n\nfrom fastapi import APIRouter\n\nfrom dashboard.services.risk_service import get_risk_alerts\n\nrouter = APIRouter()\n\n\n@router.get(\"/alerts\")\ndef risk_alerts():\n    \"\"\"\n    返回当前持仓风险预警列表。\n\n    无论成功失败都返回 200 JSON：\n      - 成功时返回预警 list（无预警为 []）\n      - 失败时返回 {\"error\": \"...\", \"alerts\": []}\n    \"\"\"\n    return get_risk_alerts()\n"}