{"path": "journal/strategy_eval_20260324.md", "language": "markdown", "kind": "journal", "lines": 93, "bytes": 2781, "truncated": false, "content": "# 策略评估报告 — 2026-03-24\n\n> 基于 5289 只 A 股真实日线数据（2013-2025），非合成数据。\n\n## 核心结论\n\n**当前策略未达到 Phase 5 上线门槛。** 需要在因子选择和风控两方面大幅改进。\n\n## 因子 IC 分析（样本内 2015-2024，5 日前瞻收益）\n\n| 因子 | IC 均值 | ICIR | IC>0% | 判断 |\n|------|---------|------|-------|------|\n| momentum_12_1 | -0.003 | -0.02 | 100% | 无效，杀掉 |\n| reversal_1m | +0.052 | 0.31 | 100% | 有效 |\n| low_vol_20d | +0.067 | 0.33 | 100% | 最强 |\n| turnover_rev | +0.065 | 0.30 | 100% | 有效 |\n\n**结论**：A 股短期反转 + 低波动 + 低换手三因子有正向预测力，中长期动量无效。\n\n## 回测结果\n\n### v1 等权全因子（含 momentum）— 样本内\n\n| 指标 | 值 |\n|------|-----|\n| 年化收益 | -17.70% |\n| 夏普 | -0.83 |\n| 最大回撤 | -95.17% |\n\n### v2 IC加权去 momentum — 样本内\n\n| 指标 | 值 |\n|------|-----|\n| 年化收益 | -0.92% |\n| 夏普 | -0.18 |\n| 最大回撤 | -83.47% |\n| v2 vs v1 | 改善明显但仍为负 |\n\n### v2 样本外（2025）\n\n| 指标 | 策略 | 沪深300 |\n|------|------|---------|\n| 年化收益 | +7.25% | +22.16% |\n| 夏普 | 0.39 | 1.34 |\n| 最大回撤 | -10.34% | -10.49% |\n\n### Walk-Forward（17 窗口）\n\n- 夏普均值: -0.75\n- 收益胜率: 47%\n- 回撤均值: -15.10%\n\n## 问题诊断\n\n### 1. 回撤 -83% 不是代码 bug\n\n2018 年低波动因子选到了一批\"之前很安静\"的小票，贸易战熊市中暴跌 50-65%。这是因子本身在极端市场的弱点。\n\n年度表现：\n- 2015: +83%（牛市）\n- 2017: -36%\n- 2018: -69%（致命打击）\n- 2019-2024: 缓慢恢复\n\n### 2. 之前 notebook 显示 \"夏普 1.12\" 是假的\n\nnotebook 加载真实数据失败后降级到 GBM 合成数据，所有指标都是在随机数据上算的，不代表真实表现。\n\n### 3. 缺失的风控\n\n当前策略没有：\n- 市场状态过滤（熊市减仓）\n- 个股回撤止损\n- 行业集中度限制\n- 最大持仓占比限制\n\n## Phase 5 门槛评审\n\n| 指标 | 门槛 | v2 实际 | 通过 |\n|------|------|---------|------|\n| 年化收益 > 15% | 15% | -0.92% | ❌ |\n| 夏普 > 0.8 | 0.8 | -0.18 | ❌ |\n| 最大回撤 < 30% | 30% | 83.47% | ❌ |\n| 回测跨度 > 3 年 | 3 年 | 9.6 年 | ✅ |\n\n## 下一步建议\n\n1. **加市场状态过滤**：用均线或波动率判断熊/牛，熊市降仓位或空仓\n2. **加行业中性化**：避免因子选股集中在某个行业\n3. **加个股止损**：单只股票跌超 X% 强制卖出\n4. **尝试更多因子**：EP（盈利收益率）、ROE 等基本面因子\n5. **优化换仓频率**：月频可能太慢，双周或周频试试\n6. **先单因子验证**：每个因子单独跑分层回测，确认真正有效后再合成\n"}