{"path": "utils/data_loader.py", "language": "python", "kind": "other", "lines": 410, "bytes": 13045, "truncated": false, "content": "\"\"\"\n数据加载模块\n支持 akshare（免费，无需注册）和 tushare（需token）\n\"\"\"\nimport logging\nimport time\nimport warnings\nfrom concurrent.futures import ThreadPoolExecutor, as_completed\n\nimport pandas as pd\nfrom pathlib import Path\nfrom tqdm import tqdm\n\nlogger = logging.getLogger(__name__)\n\nRAW_DIR = Path(__file__).parent.parent / \"data\" / \"raw\"\nPROCESSED_DIR = Path(__file__).parent.parent / \"data\" / \"processed\"\nINDEX_CACHE_DIR = RAW_DIR / \"indices\"\n\n\ndef get_stock_history(\n    symbol: str,\n    start: str,\n    end: str,\n    adjust: str = \"qfq\",  # qfq=前复权, hfq=后复权, \"\"=不复权\n    use_cache: bool = True,\n) -> pd.DataFrame:\n    \"\"\"\n    获取单只股票日线数据\n\n    参数:\n        symbol: 股票代码，如 \"000001\" （不带后缀）\n        start:  开始日期，如 \"2020-01-01\"\n        end:    结束日期，如 \"2024-12-31\"\n        adjust: 复权方式\n        use_cache: 是否使用本地缓存\n\n    返回:\n        DataFrame，列：date, open, high, low, close, volume, amount\n    \"\"\"\n    cache_path = RAW_DIR / f\"{symbol}_{start}_{end}_{adjust}.parquet\"\n    RAW_DIR.mkdir(parents=True, exist_ok=True)\n\n    if use_cache and cache_path.exists():\n        return pd.read_parquet(cache_path)\n\n    import akshare as ak\n    df = ak.stock_zh_a_hist(\n        symbol=symbol,\n        period=\"daily\",\n        start_date=start.replace(\"-\", \"\"),\n        end_date=end.replace(\"-\", \"\"),\n        adjust=adjust,\n    )\n    df = df.rename(columns={\n        \"日期\": \"date\", \"开盘\": \"open\", \"最高\": \"high\",\n        \"最低\": \"low\", \"收盘\": \"close\", \"成交量\": \"volume\",\n        \"成交额\": \"amount\", \"涨跌幅\": \"pct_change\",\n    })\n    df[\"date\"] = pd.to_datetime(df[\"date\"])\n    df = df.set_index(\"date\").sort_index()\n\n    df.to_parquet(cache_path)\n    return df\n\n\ndef get_index_history(\n    symbol: str = \"sh000300\",  # 沪深300\n    start: str = \"2020-01-01\",\n    end: str = \"2024-12-31\",\n    use_cache: bool = True,\n) -> pd.DataFrame:\n    \"\"\"\n    获取指数日线数据\n\n    常用指数代码:\n        sh000300  沪深300\n        sh000001  上证指数\n        sz399001  深证成指\n        sz399006  创业板指\n    \"\"\"\n    INDEX_CACHE_DIR.mkdir(parents=True, exist_ok=True)\n    start_ts = pd.Timestamp(start)\n    end_ts = pd.Timestamp(end)\n    cache_path = INDEX_CACHE_DIR / f\"{symbol}.parquet\"\n\n    if use_cache:\n        cached = _read_index_cache(cache_path)\n        if cached is not None and _cache_covers(cached, start_ts, end_ts):\n            return cached.loc[start:end]\n\n    errors = []\n    for fetcher in (_fetch_index_history_akshare, _fetch_index_history_baostock):\n        try:\n            df = fetcher(symbol)\n            if df is None or df.empty:\n                continue\n            df = _normalize_index_history(df)\n            subset = df.loc[start:end]\n            if subset.empty:\n                continue\n            _write_index_cache(cache_path, df)\n            return subset\n        except Exception as exc:\n            errors.append(f\"{fetcher.__name__}: {exc}\")\n\n    cached = _read_index_cache(cache_path)\n    if cached is not None:\n        subset = cached.loc[start:end]\n        if not subset.empty:\n            logger.warning(\"指数在线获取失败，回退到本地缓存: %s\", \"; \".join(errors))\n            return subset\n\n    raise RuntimeError(\n        f\"无法获取指数 {symbol} {start}~{end} 数据；已尝试 AkShare 和 BaoStock。\"\n        + (f\" 错误: {'; '.join(errors)}\" if errors else \"\")\n    )\n\n\ndef _cache_covers(df: pd.DataFrame, start: pd.Timestamp, end: pd.Timestamp) -> bool:\n    if df.empty:\n        return False\n    return df.index.min() <= start and df.index.max() >= end\n\n\ndef _read_index_cache(path: Path) -> pd.DataFrame | None:\n    if not path.exists():\n        return None\n    try:\n        return _normalize_index_history(pd.read_parquet(path))\n    except Exception as exc:\n        logger.warning(\"读取指数缓存失败 %s: %s\", path, exc)\n        return None\n\n\ndef _write_index_cache(path: Path, df: pd.DataFrame) -> None:\n    if path.exists():\n        cached = _read_index_cache(path)\n        if cached is not None and not cached.empty:\n            df = pd.concat([cached, df]).sort_index()\n            df = df[~df.index.duplicated(keep=\"last\")]\n    df.to_parquet(path)\n\n\ndef _normalize_index_history(df: pd.DataFrame) -> pd.DataFrame:\n    if \"date\" in df.columns:\n        df = df.copy()\n        df[\"date\"] = pd.to_datetime(df[\"date\"])\n        df = df.set_index(\"date\")\n    df = df.sort_index()\n    df.index = pd.to_datetime(df.index)\n    numeric_cols = [c for c in [\"open\", \"high\", \"low\", \"close\", \"volume\", \"amount\"] if c in df.columns]\n    for col in numeric_cols:\n        df[col] = pd.to_numeric(df[col], errors=\"coerce\")\n    return df\n\n\ndef _fetch_index_history_akshare(symbol: str) -> pd.DataFrame:\n    import akshare as ak\n\n    df = ak.stock_zh_index_daily(symbol=symbol)\n    return df.rename(columns={\"date\": \"date\"})\n\n\ndef _fetch_index_history_baostock(symbol: str) -> pd.DataFrame:\n    import baostock as bs\n\n    code = _to_baostock_code(symbol)\n    login = bs.login()\n    if login.error_code != \"0\":\n        raise RuntimeError(f\"BaoStock 登录失败: {login.error_msg}\")\n    try:\n        rs = bs.query_history_k_data_plus(\n            code,\n            \"date,code,open,high,low,close,volume,amount\",\n            frequency=\"d\",\n            adjustflag=\"3\",\n        )\n        if rs.error_code != \"0\":\n            raise RuntimeError(f\"BaoStock 查询失败: {rs.error_msg}\")\n        rows = []\n        while rs.next():\n            rows.append(rs.get_row_data())\n        if not rows:\n            return pd.DataFrame()\n        return pd.DataFrame(rows, columns=rs.fields)\n    finally:\n        bs.logout()\n\n\ndef _to_baostock_code(symbol: str) -> str:\n    if symbol.startswith(\"sh\"):\n        return f\"sh.{symbol[2:]}\"\n    if symbol.startswith(\"sz\"):\n        return f\"sz.{symbol[2:]}\"\n    raise ValueError(f\"不支持的指数代码格式: {symbol}\")\n\n\ndef get_hs300_stocks() -> pd.DataFrame:\n    \"\"\"获取沪深300成分股列表\"\"\"\n    import akshare as ak\n    return ak.index_stock_cons_weight_csindex(symbol=\"000300\")\n\n\ndef calc_returns(prices: pd.Series) -> pd.Series:\n    \"\"\"从价格序列计算日收益率\"\"\"\n    return prices.pct_change().dropna()\n\n\n# ─────────────────────────────────────────────\n# 批量下载\n# ─────────────────────────────────────────────\n\ndef batch_download(\n    symbols: list,\n    start: str,\n    end: str,\n    adjust: str = \"qfq\",\n    max_workers: int = 4,\n    retry: int = 2,\n    show_progress: bool = True,\n) -> dict:\n    \"\"\"\n    批量下载多只股票历史数据\n\n    参数:\n        symbols     : 股票代码列表\n        start, end  : 日期范围\n        adjust      : 复权方式\n        max_workers : 并发线程数（akshare 请求有限速，建议 ≤ 5）\n        retry       : 失败重试次数\n        show_progress: 是否显示进度条\n\n    返回:\n        {symbol: DataFrame}，失败的股票会跳过\n    \"\"\"\n    results = {}\n    errors = []\n\n    def _fetch(sym):\n        for attempt in range(retry + 1):\n            try:\n                df = get_stock_history(sym, start, end, adjust=adjust)\n                return sym, df\n            except Exception:\n                if attempt < retry:\n                    time.sleep(0.5)\n        return sym, None\n\n    with ThreadPoolExecutor(max_workers=max_workers) as executor:\n        futures = {executor.submit(_fetch, s): s for s in symbols}\n        iter_ = as_completed(futures)\n        if show_progress:\n            iter_ = tqdm(iter_, total=len(symbols), desc=\"下载中\", ncols=80)\n        for future in iter_:\n            sym, df = future.result()\n            if df is not None and not df.empty:\n                results[sym] = df\n            else:\n                errors.append(sym)\n\n    if errors:\n        warnings.warn(\n            f\"{len(errors)} 只股票下载失败: \"\n            f\"{errors[:5]}{'...' if len(errors) > 5 else ''}\"\n        )\n\n    print(f\"✅ 成功: {len(results)}/{len(symbols)} 只\")\n    return results\n\n\n# ─────────────────────────────────────────────\n# 宽表构建（date × symbol）\n# ─────────────────────────────────────────────\n\ndef build_price_matrix(\n    symbols: list,\n    start: str,\n    end: str,\n    adjust: str = \"qfq\",\n    col: str = \"close\",\n    use_cache: bool = True,\n    max_workers: int = 4,\n) -> pd.DataFrame:\n    \"\"\"\n    构建价格宽表（date × symbol），因子研究的基础数据\n\n    参数:\n        symbols     : 股票代码列表\n        start, end  : 日期范围\n        col         : 提取的列，默认 'close'（收盘价）\n        use_cache   : 是否读本地缓存\n        max_workers : 并发线程数\n\n    返回:\n        DataFrame，index=日期，columns=股票代码\n    \"\"\"\n    PROCESSED_DIR.mkdir(parents=True, exist_ok=True)\n    n = len(symbols)\n    cache_name = f\"price_wide_{col}_{start}_{end}_{adjust}_{n}stocks.parquet\"\n    cache_path = PROCESSED_DIR / cache_name\n\n    if use_cache and cache_path.exists():\n        print(f\"读取缓存: {cache_name}\")\n        return pd.read_parquet(cache_path)\n\n    stock_data = batch_download(symbols, start, end, adjust=adjust, max_workers=max_workers)\n\n    price_dict = {\n        sym: df[col]\n        for sym, df in stock_data.items()\n        if col in df.columns\n    }\n    price_wide = pd.DataFrame(price_dict).sort_index()\n    price_wide.index = pd.to_datetime(price_wide.index)\n\n    price_wide.to_parquet(cache_path)\n    print(f\"✅ 价格宽表已缓存: {cache_name}  形状: {price_wide.shape}\")\n    return price_wide\n\n\ndef build_return_matrix(price_wide: pd.DataFrame) -> pd.DataFrame:\n    \"\"\"\n    从价格宽表计算日收益率宽表（date × symbol）\n\n    使用方法:\n        price_wide = build_price_matrix(symbols, start, end)\n        ret_wide   = build_return_matrix(price_wide)\n    \"\"\"\n    return price_wide.pct_change().iloc[1:]\n\n\ndef load_price_matrix(\n    start: str,\n    end: str,\n    n_stocks: int = None,\n    col: str = \"close\",\n    adjust: str = \"qfq\",\n) -> pd.DataFrame:\n    \"\"\"\n    从缓存加载价格宽表（不重新下载）\n\n    参数:\n        n_stocks: 当初下载时的股票数量，用于匹配缓存文件名\n                  为 None 时自动搜索最新的匹配缓存\n\n    返回:\n        DataFrame 或 None（未找到缓存时）\n    \"\"\"\n    PROCESSED_DIR.mkdir(parents=True, exist_ok=True)\n\n    if n_stocks is not None:\n        path = PROCESSED_DIR / f\"price_wide_{col}_{start}_{end}_{adjust}_{n_stocks}stocks.parquet\"\n        if path.exists():\n            return pd.read_parquet(path)\n        logger.info(\"未找到宽表缓存: %s，尝试从本地 CSV 构建\", path.name)\n        return _build_price_matrix_from_local_csv(start, end, n_stocks=n_stocks, col=col)\n\n    # 自动搜索\n    pattern = f\"price_wide_{col}_{start}_{end}_{adjust}_*.parquet\"\n    matches = sorted(PROCESSED_DIR.glob(pattern))\n    if not matches:\n        logger.info(\"未找到匹配缓存 %s，尝试从本地 CSV 构建\", pattern)\n        return _build_price_matrix_from_local_csv(start, end, n_stocks=n_stocks, col=col)\n\n    path = matches[-1]  # 取最新的\n    print(f\"加载缓存: {path.name}\")\n    return pd.read_parquet(path)\n\n\ndef _build_price_matrix_from_local_csv(\n    start: str,\n    end: str,\n    n_stocks: int = None,\n    col: str = \"close\",\n) -> pd.DataFrame:\n    \"\"\"\n    从本地 CSV 数据目录直接构建价格宽表，作为旧 notebook 的兜底路径。\n\n    这条路径依赖 utils.local_data_loader 的运行时配置，不触发网络下载。\n    成功后会写入 data/processed，方便后续 notebook 直接命中缓存。\n    \"\"\"\n    try:\n        from utils.local_data_loader import get_all_symbols, load_price_wide\n    except Exception as exc:\n        logger.warning(\"无法导入 local_data_loader，无法从本地 CSV 构建宽表: %s\", exc)\n        return None\n\n    symbols = get_all_symbols()\n    if not symbols:\n        logger.warning(\"本地 CSV 目录未发现任何股票文件，无法构建宽表\")\n        return None\n\n    if n_stocks is not None:\n        symbols = symbols[:n_stocks]\n\n    wide = load_price_wide(symbols, start, end, field=col)\n    if wide is None or wide.empty:\n        logger.warning(\"从本地 CSV 构建宽表失败或结果为空: %s ~ %s\", start, end)\n        return None\n\n    cache_name = f\"price_wide_{col}_{start}_{end}_qfq_{len(wide.columns)}stocks.parquet\"\n    cache_path = PROCESSED_DIR / cache_name\n    try:\n        wide.to_parquet(cache_path)\n        logger.info(\"本地 CSV 宽表已缓存: %s\", cache_path.name)\n    except Exception as exc:\n        logger.warning(\"写入宽表缓存失败: %s\", exc)\n\n    return wide\n"}