{"path": "providers/sina_provider.py", "language": "python", "kind": "other", "lines": 201, "bytes": 6306, "truncated": false, "content": "\"\"\"\nproviders/sina_provider.py — 新浪财经实时行情 Provider\n\n提供 A 股实时行情数据，无需 API key，无注册。\n数据来源：hq.sinajs.cn（新浪财经行情接口）\n\n安全措施：\n  - 所有外部响应做字段校验和类型转换，不信任原始数据\n  - 请求带 Referer 头（Sina 要求）\n  - 单次最多 800 只（Sina 限制）\n  - 内置速率限制（默认 3 秒间隔）\n  - 连接超时 5 秒，读取超时 10 秒\n\"\"\"\nimport logging\nimport re\nimport time\nfrom typing import Dict, List\nfrom urllib.request import Request, urlopen\nfrom urllib.error import URLError\n\nimport pandas as pd\n\nlogger = logging.getLogger(__name__)\n\n# 新浪行情 URL（HTTPS）\n_SINA_URL = \"https://hq.sinajs.cn/list=\"\n_REFERER = \"https://finance.sina.com.cn\"\n_MAX_BATCH = 800  # 单次最多查询股票数\n_MIN_INTERVAL = 0.5  # 最小请求间隔（秒）\n_TIMEOUT = (5, 10)  # (connect_timeout, read_timeout)\n\n# 字段解析：新浪返回的字段顺序\n_FIELDS = [\n    \"name\", \"open\", \"prev_close\", \"price\", \"high\", \"low\",\n    \"bid1_price\", \"ask1_price\", \"volume\", \"amount\",\n    \"bid1_vol\", \"bid2_vol\", \"bid3_vol\", \"bid4_vol\", \"bid5_vol\",\n    \"bid1_p\", \"bid2_p\", \"bid3_p\", \"bid4_p\", \"bid5_p\",\n    \"ask1_vol\", \"ask2_vol\", \"ask3_vol\", \"ask4_vol\", \"ask5_vol\",\n    \"ask1_p\", \"ask2_p\", \"ask3_p\", \"ask4_p\", \"ask5_p\",\n    \"date\", \"time\", \"status\",\n]\n\n# 合法 symbol 格式校验（防注入）\n_SYMBOL_RE = re.compile(r\"^[0-9]{6}$\")\n\n\ndef _to_sina_code(symbol: str) -> str:\n    \"\"\"6 位代码转新浪格式\"\"\"\n    if not _SYMBOL_RE.match(symbol):\n        raise ValueError(f\"非法 symbol: {symbol!r}\")\n    if symbol.startswith(\"6\"):\n        return f\"sh{symbol}\"\n    return f\"sz{symbol}\"\n\n\ndef _parse_response(text: str) -> Dict[str, dict]:\n    \"\"\"\n    解析新浪行情响应文本。\n\n    返回 {symbol_6: {name, price, open, high, low, prev_close, volume, amount, ...}}\n    \"\"\"\n    results = {}\n    for line in text.strip().split(\";\"):\n        line = line.strip()\n        if not line or \"=\" not in line:\n            continue\n        # var hq_str_sh600000=\"浦发银行,10.060,...\";\n        try:\n            var_part, data_part = line.split(\"=\", 1)\n            sina_code = var_part.split(\"_\")[-1]  # sh600000\n            data = data_part.strip('\"').strip()\n            if not data:\n                continue  # 停牌或无数据\n\n            parts = data.split(\",\")\n            if len(parts) < 32:\n                continue  # 字段不足，跳过\n\n            # 提取 6 位代码\n            symbol = sina_code[2:]\n\n            # 安全解析数值字段\n            def safe_float(s):\n                try:\n                    v = float(s)\n                    return v if v >= 0 else 0.0\n                except (ValueError, TypeError):\n                    return 0.0\n\n            results[symbol] = {\n                \"name\": parts[0],\n                \"open\": safe_float(parts[1]),\n                \"prev_close\": safe_float(parts[2]),\n                \"price\": safe_float(parts[3]),\n                \"high\": safe_float(parts[4]),\n                \"low\": safe_float(parts[5]),\n                \"volume\": safe_float(parts[8]),\n                \"amount\": safe_float(parts[9]),\n                \"date\": parts[30] if len(parts) > 30 else \"\",\n                \"time\": parts[31] if len(parts) > 31 else \"\",\n            }\n        except Exception as e:\n            logger.warning(\"解析行情失败: %s\", e)\n            continue\n\n    return results\n\n\ndef fetch_realtime_quotes(symbols: List[str]) -> Dict[str, dict]:\n    \"\"\"\n    批量获取实时行情。\n\n    参数:\n        symbols: 6 位股票代码列表\n\n    返回:\n        dict: {symbol: {name, price, open, high, low, volume, amount, ...}}\n\n    异常:\n        不抛异常，失败的股票会被跳过\n    \"\"\"\n    all_results = {}\n\n    # 分批请求（每批最多 800 只）\n    for i in range(0, len(symbols), _MAX_BATCH):\n        batch = symbols[i:i + _MAX_BATCH]\n        sina_codes = []\n        for s in batch:\n            try:\n                sina_codes.append(_to_sina_code(s))\n            except ValueError:\n                continue\n\n        if not sina_codes:\n            continue\n\n        url = _SINA_URL + \",\".join(sina_codes)\n        req = Request(url, headers={\"Referer\": _REFERER})\n\n        try:\n            resp = urlopen(req, timeout=_TIMEOUT[1])\n            text = resp.read().decode(\"gbk\", errors=\"replace\")\n            batch_results = _parse_response(text)\n            all_results.update(batch_results)\n        except (URLError, Exception) as e:\n            logger.warning(\"Sina 请求失败: %s\", e)\n\n        # 速率限制\n        if i + _MAX_BATCH < len(symbols):\n            time.sleep(_MIN_INTERVAL)\n\n    return all_results\n\n\ndef get_portfolio_valuation(positions: Dict[str, int]) -> pd.DataFrame:\n    \"\"\"\n    获取持仓实时估值。\n\n    参数:\n        positions: {symbol: shares} 持仓字典\n\n    返回:\n        DataFrame: symbol, name, shares, price, value, pnl_pct\n    \"\"\"\n    symbols = list(positions.keys())\n    quotes = fetch_realtime_quotes(symbols)\n\n    rows = []\n    for sym, shares in positions.items():\n        q = quotes.get(sym)\n        if q and q[\"price\"] > 0:\n            rows.append({\n                \"symbol\": sym,\n                \"name\": q[\"name\"],\n                \"shares\": shares,\n                \"price\": q[\"price\"],\n                \"value\": q[\"price\"] * shares,\n                \"prev_close\": q[\"prev_close\"],\n                \"pnl_pct\": (q[\"price\"] / q[\"prev_close\"] - 1) if q[\"prev_close\"] > 0 else 0,\n            })\n        else:\n            rows.append({\n                \"symbol\": sym, \"name\": \"N/A\", \"shares\": shares,\n                \"price\": 0, \"value\": 0, \"prev_close\": 0, \"pnl_pct\": 0,\n            })\n\n    return pd.DataFrame(rows)\n\n\nif __name__ == \"__main__\":\n    # 快速测试\n    test_symbols = [\"600000\", \"000001\", \"600519\", \"000858\", \"601318\"]\n    print(f\"测试 {len(test_symbols)} 只股票实时行情...\\n\")\n\n    quotes = fetch_realtime_quotes(test_symbols)\n    for sym, q in quotes.items():\n        print(f\"  {q['name']:<8} ({sym}) 现价: {q['price']:.2f}  \"\n              f\"涨跌: {(q['price']/q['prev_close']-1)*100:+.2f}%  \"\n              f\"成交额: {q['amount']/1e8:.1f}亿\")\n\n    print(f\"\\n✅ sina_provider: {len(quotes)}/{len(test_symbols)} 成功\")\n"}