{"path": "scripts/rogt_v8_validation.py", "language": "python", "kind": "other", "lines": 495, "bytes": 21004, "truncated": false, "content": "\"\"\"\nROGT 策略级完整验证 — v7+ROGT (6因子) Walk-Forward + OOS分层 + 参数敏感性\n\n补全 factor_research.py 没有做的策略层面测试：\n  1. IS 组合对比  (v7 5因子 vs v7+ROGT 6因子)\n  2. Walk-Forward (6因子, train=3y, test=6m)\n  3. OOS 分层回测 (单因子 ROGT，2024)\n  4. 参数敏感性    (window=10/15/20/25/30)\n\n结果写到 journal/rogt_v8_validation_YYYYMMDD.md\n\"\"\"\nimport sys\nimport time\nimport warnings\nfrom datetime import date\nfrom pathlib import Path\n\nwarnings.filterwarnings(\"ignore\")\nsys.path.insert(0, str(Path(__file__).parent.parent))\n\nimport numpy as np\nimport pandas as pd\n\nfrom utils.local_data_loader import get_all_symbols, load_price_wide\nfrom utils.data_loader import get_index_history\nfrom utils.metrics import (\n    annualized_return, annualized_volatility, sharpe_ratio,\n    max_drawdown, win_rate, calmar_ratio,\n)\nfrom utils.factor_analysis import (\n    compute_ic_series, ic_summary,\n    quintile_backtest,\n    neutralize_factor_by_industry,\n)\nfrom utils.fundamental_loader import get_industry_classification\nfrom utils.tradability_filter import apply_tradability_filter\nfrom utils.market_regime import rsrs_regime_mask, llt_timing, higher_moment_timing\nfrom utils.alpha_factors import (\n    team_coin as _team_coin,\n    low_vol_20d as _low_vol_20d,\n    enhanced_momentum,\n    bp_factor,\n    retail_open_trap,\n)\nfrom utils.walk_forward import walk_forward_test\nfrom scripts.v6_admission_eval import run_backtest\n\n# ── 常量 ─────────────────────────────────────────────────────────\nWARMUP_START = \"2013-01-01\"\nIS_START     = \"2015-01-01\"\nIS_END       = \"2023-12-31\"   # 单因子 IS 同 factor_research.py\nOOS_START    = \"2024-01-01\"\nOOS_END      = \"2024-12-31\"\nN_STOCKS     = 30\nCOST         = 0.003\nROGT_WINDOW  = 20             # baseline 参数\n\nV7_WEIGHTS = {\n    \"team_coin\":     0.30,\n    \"low_vol_20d\":   0.25,\n    \"cgo_simple\":    0.20,\n    \"enhanced_mom_60\": 0.15,\n    \"bp\":            0.10,\n}\n\n\n# ══════════════════════════════════════════════════════════════════\n# 1. 数据加载\n# ══════════════════════════════════════════════════════════════════\n\ndef load_all_data():\n    print(\"=\" * 60)\n    print(\"[1/5] 加载数据（close / open / turnover / pb）...\")\n    t0 = time.time()\n    symbols = get_all_symbols()\n\n    close    = load_price_wide(symbols, WARMUP_START, OOS_END, field=\"close\")\n    open_p   = load_price_wide(symbols, WARMUP_START, OOS_END, field=\"open\")\n    turnover = load_price_wide(symbols, WARMUP_START, OOS_END, field=\"turnover\")\n\n    # 只保留 close 有效的股票（open/turnover 对齐）\n    valid_syms = close.columns[close.notna().sum() > 500]\n    close    = close[valid_syms]\n    open_p   = open_p.reindex(columns=valid_syms)\n    turnover = turnover.reindex(columns=valid_syms)\n\n    # PB 宽表（直接从本地 CSV 加载，字段 \"pb\" = 市净率）\n    pb = load_price_wide(symbols, WARMUP_START, OOS_END, field=\"pb\").reindex(\n        index=close.index, columns=valid_syms\n    )\n\n    # HS300 基准\n    hs300 = None\n    try:\n        idx = get_index_history(symbol=\"sh000300\", start=WARMUP_START, end=OOS_END)\n        hs300 = idx[\"close\"].reindex(close.index)\n    except Exception as e:\n        print(f\"  HS300 不可用: {e}\")\n\n    tradable = apply_tradability_filter(close)\n\n    print(f\"  股票数: {len(valid_syms)} | 交易日: {len(close)} | 耗时: {time.time()-t0:.1f}s\")\n    return close, open_p, turnover, pb, hs300, tradable\n\n\n# ══════════════════════════════════════════════════════════════════\n# 2. 因子构建\n# ══════════════════════════════════════════════════════════════════\n\ndef build_six_factors(close, open_p, turnover, pb, window=ROGT_WINDOW):\n    \"\"\"构建 v7 5因子 + ROGT，返回两个 dict（raw, 中性化）\"\"\"\n    print(f\"\\n[2/5] 构建 6 因子（ROGT window={window}）...\")\n    factors = {\n        \"team_coin\":      _team_coin(close),\n        \"low_vol_20d\":    _low_vol_20d(close),\n        \"cgo_simple\":     -(close / close.rolling(60).mean() - 1),\n        \"enhanced_mom_60\": enhanced_momentum(close, window=60),\n        \"bp\":             bp_factor(pb).reindex_like(close),\n        \"rogt\":           retail_open_trap(close, open_p, turnover, window=window),\n    }\n    symbols = list(close.columns)\n    industry_df = get_industry_classification(symbols=symbols, use_cache=True)\n    neutral = {\n        name: neutralize_factor_by_industry(fac, industry_df, show_progress=False)\n        for name, fac in factors.items()\n    }\n    print(f\"  行业覆盖: {len(industry_df)} 只\")\n    return factors, neutral, industry_df\n\n\n# ══════════════════════════════════════════════════════════════════\n# 3. IS 组合对比\n# ══════════════════════════════════════════════════════════════════\n\ndef calc_metrics(ret):\n    if ret is None or len(ret) == 0:\n        return {}\n    return {\n        \"ann\":    annualized_return(ret),\n        \"vol\":    annualized_volatility(ret),\n        \"sr\":     sharpe_ratio(ret),\n        \"mdd\":    max_drawdown(ret),\n        \"calmar\": calmar_ratio(ret),\n        \"wr\":     win_rate(ret),\n    }\n\n\ndef run_is_comparison(close, neutral, tradable, hs300):\n    \"\"\"对比 v7(5因子) vs v7+ROGT(6因子) IS 表现\"\"\"\n    print(\"\\n[3/5] IS 组合对比...\")\n\n    regime_mask = None\n    if hs300 is not None:\n        try:\n            hs300_full = get_index_history(symbol=\"sh000300\", start=WARMUP_START, end=OOS_END)\n            r = rsrs_regime_mask(hs300_full[\"high\"], hs300_full[\"low\"])\n            l = llt_timing(hs300_full[\"close\"])\n            h = higher_moment_timing(hs300_full[\"close\"], order=5)\n            c = r.index.intersection(l.index).intersection(h.index)\n            vote = r.loc[c].astype(int) + l.loc[c].astype(int) + h.loc[c].astype(int)\n            regime_mask = vote >= 2\n        except Exception as e:\n            print(f\"  择时不可用: {e}\")\n\n    # v7 (5因子，不含 rogt)\n    weights_5 = {k: v for k, v in V7_WEIGHTS.items()}\n    neutral_5 = {k: v for k, v in neutral.items() if k != \"rogt\"}\n\n    ret_v7 = run_backtest(\n        close, neutral_5, weights_5, n_stocks=N_STOCKS, cost=COST,\n        mask=tradable, regime_mask=regime_mask, lag1=True,\n    )\n\n    # v7+ROGT (6因子，IC加权方式直接用 ICIR 比例给 ROGT)\n    fwd = close.pct_change(5).shift(-5)\n    rogt_ic = compute_ic_series(\n        neutral[\"rogt\"].loc[IS_START:IS_END],\n        fwd.loc[IS_START:IS_END],\n        method=\"spearman\", min_stocks=50,\n    )\n    rogt_icir = abs(ic_summary(rogt_ic)[\"ICIR\"])\n\n    # 给 ROGT 与其他因子等比例的 ICIR 权重（scale 到 10% ~ 20%）\n    # 简单做法：按 ICIR 比例，ROGT 约占全部 ICIR 总和的一份\n    base_icirs = {\n        \"team_coin\": 0.3,\n        \"low_vol_20d\": 0.25,\n        \"cgo_simple\": 0.18,\n        \"enhanced_mom_60\": 0.12,\n        \"bp\": 0.08,\n    }\n    all_icirs = {**base_icirs, \"rogt\": rogt_icir}\n    total = sum(all_icirs.values())\n    weights_6 = {k: v / total for k, v in all_icirs.items()}\n\n    ret_v8 = run_backtest(\n        close, neutral, weights_6, n_stocks=N_STOCKS, cost=COST,\n        mask=tradable, regime_mask=regime_mask, lag1=True,\n    )\n\n    results = {}\n    for label, ret in [(\"v7_5factor\", ret_v7), (\"v7_plus_rogt_6factor\", ret_v8)]:\n        is_ret  = ret.loc[IS_START:IS_END]\n        oos_ret = ret.loc[OOS_START:OOS_END]\n        results[label] = {\n            \"is\":  calc_metrics(is_ret),\n            \"oos\": calc_metrics(oos_ret) if len(oos_ret) > 20 else {},\n        }\n        m = results[label][\"is\"]\n        print(f\"  {label} IS: 年化={m.get('ann',0):+.2%} 夏普={m.get('sr',0):.4f} 回撤={m.get('mdd',0):.2%}\")\n\n    return results, regime_mask, weights_6\n\n\n# ══════════════════════════════════════════════════════════════════\n# 4. Walk-Forward (6因子)\n# ══════════════════════════════════════════════════════════════════\n\ndef run_walk_forward_6factor(close, open_p, turnover, pb, tradable, regime_mask):\n    \"\"\"v7+ROGT 6因子 Walk-Forward（train=3y, test=6m）\"\"\"\n    print(\"\\n[4/5] Walk-Forward 验证（6因子 + ROGT）...\")\n\n    symbols = list(close.columns)\n    pb_full = pb.reindex(index=close.index, columns=symbols)\n\n    def wf_fn(price_slice, _fdata, train_start, train_end, test_start, test_end):\n        # 用 price_slice 的时间范围从全量数据中切片\n        open_slice   = open_p.reindex(index=price_slice.index, columns=price_slice.columns)\n        turn_slice   = turnover.reindex(index=price_slice.index, columns=price_slice.columns)\n        pb_slice     = pb_full.reindex(index=price_slice.index, columns=price_slice.columns)\n\n        # 构建 6 因子（全窗口）\n        local_factors = {\n            \"team_coin\":      _team_coin(price_slice),\n            \"low_vol_20d\":    _low_vol_20d(price_slice),\n            \"cgo_simple\":     -(price_slice / price_slice.rolling(60).mean() - 1),\n            \"enhanced_mom_60\": enhanced_momentum(price_slice, window=60),\n            \"rogt\":           retail_open_trap(price_slice, open_slice, turn_slice, window=ROGT_WINDOW),\n        }\n        try:\n            local_factors[\"bp\"] = bp_factor(pb_slice).reindex_like(price_slice)\n        except Exception:\n            pass\n\n        # 行业中性化\n        industry_df = get_industry_classification(symbols=symbols, use_cache=True)\n        neutral_factors = {\n            name: neutralize_factor_by_industry(fac, industry_df, show_progress=False)\n            for name, fac in local_factors.items()\n        }\n\n        # IC 加权权重（训练期）\n        local_fwd = price_slice.pct_change(5).shift(-5)\n        local_fwd_train = local_fwd.loc[train_start:train_end]\n\n        local_weights = {}\n        for name, fac in neutral_factors.items():\n            fac_train = fac.loc[train_start:train_end]\n            ic_s = compute_ic_series(fac_train, local_fwd_train, method=\"spearman\", min_stocks=50)\n            if len(ic_s) > 10:\n                m = ic_s.mean()\n                if m > 0:\n                    local_weights[name] = m\n\n        if not local_weights:\n            return pd.Series(dtype=float)\n\n        total = sum(local_weights.values())\n        local_weights = {k: v / total for k, v in local_weights.items()}\n\n        wf_ret = run_backtest(\n            price_slice, neutral_factors, local_weights, n_stocks=N_STOCKS,\n            cost=COST, mask=None, regime_mask=regime_mask, lag1=True,\n        )\n        return wf_ret.loc[test_start:test_end] if len(wf_ret) > 0 else pd.Series(dtype=float)\n\n    wf_summary = None\n    wf_df = None\n    try:\n        wf_df = walk_forward_test(\n            wf_fn, close.loc[WARMUP_START:IS_END], {},\n            train_years=3, test_months=6,\n        )\n        valid = wf_df[wf_df[\"sharpe\"].notna()]\n        wf_summary = {\n            \"windows\":       len(wf_df),\n            \"valid\":         len(valid),\n            \"sharpe_mean\":   valid[\"sharpe\"].mean(),\n            \"sharpe_median\": valid[\"sharpe\"].median(),\n            \"return_mean\":   valid[\"total_return\"].mean(),\n            \"win_rate\":      (valid[\"total_return\"] > 0).mean(),\n            \"mdd_mean\":      valid[\"max_drawdown\"].mean(),\n        }\n        print(f\"  窗口: {wf_summary['windows']} | 有效: {wf_summary['valid']}\")\n        print(f\"  夏普均值: {wf_summary['sharpe_mean']:.4f} | 中位数: {wf_summary['sharpe_median']:.4f}\")\n        print(f\"  收益均值: {wf_summary['return_mean']:+.2%} | 胜率: {wf_summary['win_rate']:.0%}\")\n        print(f\"  回撤均值: {wf_summary['mdd_mean']:.2%}\")\n    except Exception as e:\n        print(f\"  WF 失败: {e}\")\n        import traceback; traceback.print_exc()\n\n    return wf_summary, wf_df\n\n\n# ══════════════════════════════════════════════════════════════════\n# 5. OOS 分层回测（单因子 ROGT，2024）\n# ══════════════════════════════════════════════════════════════════\n\ndef run_oos_quintile(close, open_p, turnover):\n    \"\"\"在 OOS（2024）期验证 ROGT 分层单调性\"\"\"\n    print(\"\\n[5a] OOS 分层回测（ROGT，2024）...\")\n    factor_wide = retail_open_trap(close, open_p, turnover, window=ROGT_WINDOW)\n    ret_wide    = close.pct_change().shift(-1)\n\n    f_oos = factor_wide.loc[OOS_START:OOS_END]\n    r_oos = ret_wide.loc[OOS_START:OOS_END]\n\n    try:\n        quintile_stats, ls_ret = quintile_backtest(f_oos, r_oos, n_groups=5)\n        ann_ls = ls_ret.mean() * 252\n        sr_ls  = ls_ret.mean() / (ls_ret.std() + 1e-10) * np.sqrt(252)\n        print(f\"  多空年化: {ann_ls:.2%} | 多空夏普: {sr_ls:.4f}\")\n        for q, row in quintile_stats.iterrows():\n            ann = row.get(\"annual_return\", row.get(\"ann_return\", float(\"nan\")))\n            print(f\"  Q{q}: {ann:.2%}\")\n        return quintile_stats, ls_ret\n    except Exception as e:\n        print(f\"  OOS 分层失败: {e}\")\n        import traceback; traceback.print_exc()\n        return None, pd.Series(dtype=float)\n\n\n# ══════════════════════════════════════════════════════════════════\n# 6. 参数敏感性（window）\n# ══════════════════════════════════════════════════════════════════\n\ndef run_param_sensitivity(close, open_p, turnover):\n    \"\"\"测试不同 window 对 IS IC 的影响\"\"\"\n    print(\"\\n[5b] 参数敏感性（window=10/15/20/25/30）...\")\n    ret_wide = close.pct_change().shift(-1)\n    rows = []\n    for w in [10, 15, 20, 25, 30]:\n        fac = retail_open_trap(close, open_p, turnover, window=w)\n        f_is = fac.loc[IS_START:IS_END]\n        r_is = ret_wide.loc[IS_START:IS_END]\n        ic_s = compute_ic_series(f_is, r_is, method=\"spearman\", min_stocks=50)\n        s = ic_summary(ic_s)\n        rows.append({\n            \"window\": w,\n            \"IC_mean\": s[\"IC_mean\"],\n            \"ICIR\":    s[\"ICIR\"],\n            \"t_stat\":  s[\"t_stat\"],\n            \"pct_pos\": s[\"pct_pos\"],\n        })\n        print(f\"  window={w:2d}: IC={s['IC_mean']:.4f}  ICIR={s['ICIR']:.4f}  t={s['t_stat']:.2f}\")\n    return pd.DataFrame(rows)\n\n\n# ══════════════════════════════════════════════════════════════════\n# 7. 报告生成\n# ══════════════════════════════════════════════════════════════════\n\ndef write_report(is_results, wf_summary, oos_quintile, param_df, weights_6):\n    out = Path(__file__).parent.parent / \"journal\" / f\"rogt_v8_validation_{date.today().strftime('%Y%m%d')}.md\"\n\n    lines = [\n        f\"# ROGT 策略级验证报告 — v7+ROGT 6因子 — {date.today()}\",\n        \"\",\n        \"## 1. IS 组合对比\",\n        \"\",\n        \"| 组合 | 年化 | 夏普 | 最大回撤 |\",\n        \"| --- | ---: | ---: | ---: |\",\n    ]\n\n    for label, res in is_results.items():\n        m = res[\"is\"]\n        lines.append(\n            f\"| {label} | {m.get('ann',0):+.2%} | {m.get('sr',0):.4f} | {m.get('mdd',0):.2%} |\"\n        )\n\n    lines += [\n        \"\",\n        \"## 2. Walk-Forward 结果（6因子，train=3y, test=6m）\",\n        \"\",\n    ]\n    if wf_summary:\n        lines += [\n            f\"| 窗口数 | 有效窗口 | 夏普均值 | **夏普中位数** | 收益均值 | 胜率 | 回撤均值 |\",\n            f\"| --- | --- | --- | --- | --- | --- | --- |\",\n            f\"| {wf_summary['windows']} | {wf_summary['valid']} \"\n            f\"| {wf_summary['sharpe_mean']:.4f} | **{wf_summary['sharpe_median']:.4f}** \"\n            f\"| {wf_summary['return_mean']:+.2%} | {wf_summary['win_rate']:.0%} \"\n            f\"| {wf_summary['mdd_mean']:.2%} |\",\n            \"\",\n        ]\n        med = wf_summary['sharpe_median']\n        if med > 0.3:\n            verdict_wf = \"✅ 中位数 > 0.3，WF 稳健\"\n        elif med > 0.0:\n            verdict_wf = \"⚠️ 中位数 > 0 但 < 0.3，踩线\"\n        else:\n            verdict_wf = \"❌ 中位数 ≤ 0，WF 不稳定\"\n        lines.append(f\"**WF 判断**：{verdict_wf}\")\n    else:\n        lines.append(\"WF 未能运行（见控制台输出）\")\n\n    lines += [\n        \"\",\n        \"## 3. OOS 分层回测（ROGT 单因子，2024）\",\n        \"\",\n    ]\n    if oos_quintile is not None:\n        lines += [\"| 分位数 | 年化收益 |\", \"| --- | ---: |\"]\n        for q, row in oos_quintile.iterrows():\n            ann = row.get(\"annual_return\", row.get(\"ann_return\", float(\"nan\")))\n            lines.append(f\"| Q{q} | {ann:.2%} |\")\n    else:\n        lines.append(\"OOS 分层未能运行\")\n\n    lines += [\n        \"\",\n        \"## 4. 参数敏感性（window）\",\n        \"\",\n        \"| window | IC均值 | ICIR | t-stat | IC>0% |\",\n        \"| --- | ---: | ---: | ---: | ---: |\",\n    ]\n    for _, row in param_df.iterrows():\n        lines.append(\n            f\"| {int(row['window'])} | {row['IC_mean']:.4f} | {row['ICIR']:.4f} \"\n            f\"| {row['t_stat']:.2f} | {row['pct_pos']:.1%} |\"\n        )\n\n    lines += [\n        \"\",\n        \"## 5. v8 因子权重（ICIR比例）\",\n        \"\",\n        \"| 因子 | 权重 |\",\n        \"| --- | ---: |\",\n    ]\n    for k, v in weights_6.items():\n        lines.append(f\"| {k} | {v:.3f} |\")\n\n    lines += [\n        \"\",\n        \"## 6. 最终裁定\",\n        \"\",\n    ]\n\n    # 综合判断\n    v7_sr   = is_results[\"v7_5factor\"][\"is\"].get(\"sr\", 0)\n    v8_sr   = is_results[\"v7_plus_rogt_6factor\"][\"is\"].get(\"sr\", 0)\n    improve = v8_sr - v7_sr\n\n    if wf_summary:\n        med = wf_summary['sharpe_median']\n        if med > 0.0 and improve > 0:\n            verdict = f\"**READY** — WF 中位数 {med:.4f} > 0，IS 夏普提升 {improve:+.4f}，ROGT 可正式纳入 v8。\"\n        elif med > 0.0:\n            verdict = f\"**CONDITIONAL** — WF 中位数 {med:.4f} > 0，但 IS 未提升（{improve:+.4f}），重新评估权重。\"\n        else:\n            verdict = f\"**DEFER** — WF 中位数 {med:.4f} ≤ 0，6因子 WF 不稳定，ROGT 加入不能改善策略健壮性。\"\n    else:\n        verdict = \"**INCONCLUSIVE** — WF 未能运行，无法给出最终裁定。\"\n\n    lines.append(verdict)\n    lines += [\"\", f\"数据来源：外盘数据 `/Volumes/Crucial X10/20260320/`，IS {IS_START}~{IS_END}，OOS {OOS_START}~{OOS_END}\"]\n\n    out.write_text(\"\\n\".join(lines), encoding=\"utf-8\")\n    print(f\"\\n报告已写入: {out}\")\n    return out\n\n\n# ══════════════════════════════════════════════════════════════════\n# Main\n# ══════════════════════════════════════════════════════════════════\n\ndef main():\n    t_total = time.time()\n\n    close, open_p, turnover, pb, hs300, tradable = load_all_data()\n    factors, neutral, industry_df = build_six_factors(close, open_p, turnover, pb)\n\n    is_results, regime_mask, weights_6 = run_is_comparison(close, neutral, tradable, hs300)\n    wf_summary, wf_df = run_walk_forward_6factor(close, open_p, turnover, pb, tradable, regime_mask)\n    oos_quintile, oos_ls = run_oos_quintile(close, open_p, turnover)\n    param_df = run_param_sensitivity(close, open_p, turnover)\n\n    report_path = write_report(is_results, wf_summary, oos_quintile, param_df, weights_6)\n\n    print(f\"\\n完成，总耗时 {(time.time()-t_total)/60:.1f} 分钟\")\n    print(f\"报告：{report_path}\")\n\n\nif __name__ == \"__main__\":\n    main()\n"}