{"path": "strategies/multi_factor.py", "language": "python", "kind": "backtest", "lines": 446, "bytes": 17885, "truncated": false, "content": "\"\"\"\n多因子选股策略\n流程：每月换仓，截面分位数合成综合评分，选前 N 只等权持有\n\"\"\"\nfrom __future__ import annotations\n\nimport logging\nimport warnings\nimport numpy as np\nimport pandas as pd\nfrom typing import Optional\n\nfrom strategies.base import BaseStrategy, StrategyConfig\n\n_log = logging.getLogger(__name__)\n\n\nclass MultiFactorStrategy(BaseStrategy):\n    \"\"\"\n    多因子选股策略\n\n    流程：\n        1. 每月第一个交易日调仓\n        2. 计算各因子截面分位数\n        3. 合成综合评分（只用 ICIR 显著的因子）\n        4. 选前 N 只（默认30只），等权持有\n        5. 排除 ST 股票、上市不足60日的次新股\n        6. 扣除双边 0.3% 交易成本\n    \"\"\"\n\n    description = \"多因子等权选股策略，月频换仓\"\n    hypothesis = \"多因子综合评分能捕捉截面收益差异，分散化持有降低个股风险\"\n    references = [\"Fama-French 多因子模型\", \"IC加权合成方法\"]\n\n    def __init__(\n        self,\n        config: StrategyConfig,\n        factors: dict,                        # {factor_name: (factor_wide_df, direction)}\n        is_st_wide: Optional[pd.DataFrame] = None,  # ST标记宽表（日期×股票，1=ST）\n        n_stocks: int = 30,\n        rebalance_freq: str = \"monthly\",\n        neutralize: bool = False,\n        industry_map: Optional[dict] = None,  # {symbol: industry_name}\n        ic_weighting: bool = False,           # 是否用 ICIR 加权替代等权合成\n    ):\n        \"\"\"\n        初始化多因子策略\n\n        参数:\n            config         : 策略配置\n            factors        : 因子字典，{名称: (宽表DataFrame, 方向)}\n                             宽表格式为 date × symbol，方向1为正向，-1为反向\n            is_st_wide     : ST标记宽表，date × symbol，1表示ST股（可选）\n            n_stocks       : 每次选股数量\n            rebalance_freq : 调仓频率，目前仅支持 \"monthly\"\n            neutralize     : 是否对各因子做行业中性化（需同时提供 industry_map）\n            industry_map   : {symbol: industry_name}，行业分类字典；\n                             neutralize=True 时必须提供，否则打 warning 并跳过中性化\n            ic_weighting   : 是否启用自适应 ICIR 加权合成；\n                             True 时用近 60 日 ICIR softmax 权重替代等权平均，\n                             数据不足 60 日时自动降级为等权\n        \"\"\"\n        super().__init__(config)\n        self.factors = factors\n        self.is_st_wide = is_st_wide\n        self.n_stocks = n_stocks\n        self.rebalance_freq = rebalance_freq\n        self.neutralize = neutralize\n        self.industry_map = industry_map\n        self.ic_weighting = ic_weighting\n        self.trade_log: list = []  # 调仓记录\n\n        # 预先将 industry_map 转为 pd.Series，后续重复使用\n        if self.neutralize and self.industry_map:\n            self._industry_series = pd.Series(self.industry_map)\n        else:\n            self._industry_series = None\n\n        # IC 权重月度缓存\n        self._ic_weights_cache: dict = {}          # {factor_name: weight}\n        self._ic_weights_last_update: Optional[object] = None  # 上次更新的年月 (year, month)\n\n    @staticmethod\n    def _winsorize_zscore(series: pd.Series, sigma: float = 3.0) -> pd.Series:\n        \"\"\"\n        截面3sigma缩尾后标准化\n\n        参数:\n            series: 截面因子值\n            sigma: 缩尾倍数\n\n        返回:\n            标准化后的 Series\n        \"\"\"\n        mean = series.mean()\n        std = series.std()\n        if std == 0 or np.isnan(std):\n            return pd.Series(np.zeros(len(series)), index=series.index)\n        lower = mean - sigma * std\n        upper = mean + sigma * std\n        clipped = series.clip(lower, upper)\n        return (clipped - clipped.mean()) / clipped.std()\n\n    def _compute_ic_weights(self, price_wide: pd.DataFrame) -> dict:\n        \"\"\"\n        计算各因子近期 ICIR 加权权重。\n\n        用前 60 日数据计算每个因子的 IC 序列，取 ICIR = mean/std。\n        权重 = softmax 归一化后的 |ICIR_i|，代表每个因子的边际贡献权重。\n\n        如果可用历史数据不足 60 日（bootstrap 期），返回 None，\n        调用方负责降级为等权。\n\n        参数:\n            price_wide : 价格宽表 (date × symbol)，用于构造次日收益率\n\n        返回:\n            dict {factor_name: weight}，sum=1；或 None（数据不足）\n        \"\"\"\n        from utils.factor_analysis import compute_ic_series\n\n        # 次日收益率（shift(-1) 得到当日对应的次日收益）\n        ret_wide = price_wide.pct_change().shift(-1)\n\n        icirs = {}\n        for name, (factor_df, direction) in self.factors.items():\n            try:\n                ic_s = compute_ic_series(factor_df, ret_wide, min_stocks=20)\n                clean = ic_s.dropna().tail(60)\n                # bootstrap 期：全局可用 IC 不足 20 条，返回 None 触发等权降级\n                if len(clean) < 20:\n                    return None\n                icir = abs(clean.mean() / clean.std()) if clean.std() > 0 else 0.0\n                icirs[name] = icir\n            except Exception:\n                icirs[name] = 0.01  # 单因子失败时给最小权重 fallback\n\n        if not icirs or max(icirs.values()) == 0:\n            # 全部因子 ICIR 为零，等权 fallback\n            n = len(self.factors)\n            return {k: 1.0 / n for k in self.factors}\n\n        # Softmax 归一化（sum 归一）\n        total = sum(icirs.values())\n        return {k: v / total for k, v in icirs.items()}\n\n    def generate_signals(\n        self,\n        data: pd.DataFrame,\n        ic_weights: Optional[dict] = None,\n    ) -> pd.DataFrame:\n        \"\"\"\n        生成多因子综合评分信号\n\n        流程（neutralize=True 且有 industry_map 时）：\n            1. 截面 3σ 缩尾后 z-score 标准化\n            2. 行业内 demean（industry_neutralize_fast）去除行业暴露\n            3. 方向调整后合成：若 ic_weights 不为 None 则加权平均，否则等权平均\n\n        参数:\n            data       : 未使用（信号来自 self.factors），保留接口兼容性\n            ic_weights : 可选的因子权重 dict {factor_name: weight}，\n                         由 run() 通过 _compute_ic_weights 传入；\n                         None 表示等权合成\n\n        返回:\n            综合评分宽表 DataFrame（date × symbol）\n        \"\"\"\n        # 确定是否执行中性化，并在需要时做提前校验\n        do_neutralize = self.neutralize\n        if do_neutralize:\n            if self._industry_series is None:\n                warnings.warn(\n                    \"MultiFactorStrategy: neutralize=True 但未提供 industry_map，\"\n                    \"跳过行业中性化。请在构造时传入 industry_map={symbol: industry_name}。\",\n                    stacklevel=2,\n                )\n                do_neutralize = False\n            else:\n                from utils.factor_analysis import industry_neutralize_fast\n\n        all_scores = {}  # factor_name -> 调整后 z-score DataFrame\n\n        for factor_name, (factor_df, direction) in self.factors.items():\n            # 1. 截面 z-score（逐行/逐日计算）\n            zscore = factor_df.apply(self._winsorize_zscore, axis=1)\n\n            # 2. 行业中性化（在 z-score 后、方向调整前）\n            if do_neutralize:\n                try:\n                    zscore = industry_neutralize_fast(zscore, self._industry_series)\n                    _log.debug(\"因子 %s 行业中性化完成\", factor_name)\n                except Exception as exc:\n                    _log.warning(\"因子 %s 行业中性化失败，使用原始 z-score: %s\", factor_name, exc)\n\n            # 3. 方向调整：direction=-1 时反转\n            zscore = zscore * direction\n            all_scores[factor_name] = zscore\n\n        if not all_scores:\n            raise ValueError(\"factors 字典为空，无法生成信号\")\n\n        factor_names = list(all_scores.keys())\n        score_list = [all_scores[n] for n in factor_names]\n\n        if ic_weights is not None:\n            # IC 加权合成：每个因子 z-score 乘对应权重后相加\n            # 权重之和为 1，直接做加权 sum 等价于加权 mean\n            weighted_list = [\n                score_list[i] * ic_weights.get(factor_names[i], 1.0 / len(factor_names))\n                for i in range(len(factor_names))\n            ]\n            composite = pd.concat(weighted_list, keys=factor_names).groupby(level=1).sum()\n        else:\n            # 等权合成（原逻辑）\n            composite = pd.concat(score_list, keys=factor_names).groupby(level=1).mean()\n\n        composite = composite.sort_index()\n        return composite\n\n    def _get_rebalance_dates(self, dates: pd.DatetimeIndex) -> list:\n        \"\"\"\n        获取调仓日期（每月第一个交易日）\n\n        参数:\n            dates: 所有交易日序列\n\n        返回:\n            调仓日期列表\n        \"\"\"\n        rebalance_dates = []\n        prev_month = None\n        for dt in dates:\n            month = (dt.year, dt.month)\n            if month != prev_month:\n                rebalance_dates.append(dt)\n                prev_month = month\n        return rebalance_dates\n\n    def run(self, price_wide: pd.DataFrame) -> pd.DataFrame:\n        \"\"\"\n        运行回测\n\n        参数:\n            price_wide: 价格宽表，date × symbol，值为收盘价\n\n        关键约束:\n            - 信号必须 .shift(1) 才能用于交易（无未来函数）\n            - 排除 ST 股（is_st == 1）\n            - 交易成本双边 0.3%（每次换手扣除）\n            - 返回 DataFrame 包含: date, portfolio_return, cumulative_return\n        \"\"\"\n        # 1. 计算 IC 权重（月度缓存），然后生成综合评分\n        ic_weights: Optional[dict] = None\n        if self.ic_weighting:\n            # 用价格宽表末尾时间点的年月判断是否需要刷新缓存\n            last_date = price_wide.index[-1]\n            current_ym = (last_date.year, last_date.month)\n            if self._ic_weights_last_update != current_ym:\n                weights = self._compute_ic_weights(price_wide)\n                if weights is None:\n                    # bootstrap 期：数据不足，降级等权\n                    _log.info(\"IC权重bootstrap期，使用等权合成\")\n                    self._ic_weights_cache = {}\n                else:\n                    self._ic_weights_cache = weights\n                    self._ic_weights_last_update = current_ym\n                    _log.info(\n                        \"IC权重已更新 (%d-%02d): %s\",\n                        current_ym[0], current_ym[1],\n                        {k: f\"{v:.3f}\" for k, v in weights.items()},\n                    )\n            # 缓存非空才启用加权，否则维持等权（None）\n            ic_weights = self._ic_weights_cache if self._ic_weights_cache else None\n\n        composite_score = self.generate_signals(price_wide, ic_weights=ic_weights)\n\n        # 2. 排除 ST 股票（评分置零）\n        if self.is_st_wide is not None:\n            st_aligned = self.is_st_wide.reindex(\n                index=composite_score.index,\n                columns=composite_score.columns\n            ).fillna(0)\n            composite_score = composite_score.where(st_aligned != 1, other=np.nan)\n\n        # 3. 将信号 shift(1)，避免未来函数\n        signal_shifted = composite_score.shift(1)\n\n        # 4. 计算日收益率\n        daily_returns = price_wide.pct_change()\n\n        # 确保时间对齐\n        common_dates = price_wide.index.intersection(signal_shifted.index)\n        daily_returns = daily_returns.loc[common_dates]\n        signal_shifted = signal_shifted.reindex(common_dates)\n\n        # 5. 确定调仓日期\n        rebalance_dates = self._get_rebalance_dates(common_dates)\n\n        # 6. 逐期回测\n        portfolio_returns = []\n        current_holdings: set = set()  # 当前持仓股票集合\n        current_weights: dict = {}     # 当前持仓权重 {symbol: weight}\n        self.trade_log = []\n\n        rebalance_set = set(rebalance_dates)\n\n        for i, date in enumerate(common_dates):\n            if date in rebalance_set:\n                # 选股：取当日 shifted 信号，选 top n_stocks\n                scores_today = signal_shifted.loc[date].dropna()\n                if len(scores_today) >= self.n_stocks:\n                    selected = scores_today.nlargest(self.n_stocks).index.tolist()\n                elif len(scores_today) > 0:\n                    selected = scores_today.nlargest(len(scores_today)).index.tolist()\n                else:\n                    selected = list(current_holdings)\n\n                new_holdings = set(selected)\n                n = len(new_holdings)\n                new_weights = {s: 1.0 / n for s in new_holdings} if n > 0 else {}\n\n                # 计算换手率（卖出权重 + 买入权重）/ 2，即双边换手\n                all_symbols = current_holdings | new_holdings\n                turnover = 0.0\n                for sym in all_symbols:\n                    old_w = current_weights.get(sym, 0.0)\n                    new_w = new_weights.get(sym, 0.0)\n                    turnover += abs(new_w - old_w)\n                # turnover 已是双边（买入权重变化 + 卖出权重变化之和）\n                # commission 是单边费率，turnover 已含买卖两边，不需要再 ×2\n                transaction_cost = self.config.commission * turnover\n\n                # 记录调仓\n                buys = sorted(new_holdings - current_holdings)\n                sells = sorted(current_holdings - new_holdings)\n                self.trade_log.append({\n                    \"date\": str(date.date()) if hasattr(date, 'date') else str(date),\n                    \"n_holdings\": n,\n                    \"n_buys\": len(buys),\n                    \"n_sells\": len(sells),\n                    \"buys\": buys,\n                    \"sells\": sells,\n                    \"turnover\": round(turnover, 4),\n                    \"cost\": round(transaction_cost, 6),\n                })\n\n                current_holdings = new_holdings\n                current_weights = new_weights\n            else:\n                transaction_cost = 0.0\n\n            # 计算当日组合收益（等权）\n            if current_holdings:\n                ret_today = daily_returns.loc[date, list(current_holdings)].mean()\n                if pd.isna(ret_today):\n                    ret_today = 0.0\n            else:\n                ret_today = 0.0\n\n            portfolio_returns.append(ret_today - transaction_cost)\n\n        # 7. 组装结果\n        results = pd.DataFrame(\n            {\"portfolio_return\": portfolio_returns},\n            index=common_dates,\n        )\n        results[\"cumulative_return\"] = (1 + results[\"portfolio_return\"]).cumprod() - 1\n\n        # 存储到 self.results（兼容基类接口）\n        self.results = results.rename(columns={\"portfolio_return\": \"returns\"})\n        self.results[\"cumulative_return\"] = results[\"cumulative_return\"]\n        self.results[\"positions\"] = self.n_stocks\n        self.results[\"equity\"] = (\n            self.config.initial_capital\n            * (1 + results[\"portfolio_return\"]).cumprod()\n        )\n\n        # 返回用户友好格式\n        output = results.copy()\n        output.index.name = \"date\"\n        return output\n\n\nif __name__ == \"__main__\":\n    print(MultiFactorStrategy.__doc__)\n\n    # 最小验证：构造假数据，确认可以实例化和运行\n    import numpy as np\n\n    np.random.seed(42)\n    dates = pd.date_range(\"2020-01-01\", periods=500, freq=\"B\")\n    symbols = [f\"00{i:04d}.SZ\" for i in range(1, 51)]\n\n    price_wide = pd.DataFrame(\n        np.cumprod(1 + np.random.randn(500, 50) * 0.01, axis=0),\n        index=dates,\n        columns=symbols,\n    )\n    factor_df = pd.DataFrame(\n        np.random.randn(500, 50),\n        index=dates,\n        columns=symbols,\n    )\n    is_st = pd.DataFrame(0, index=dates, columns=symbols)\n\n    # 构造假的行业分类：每10只股票一个行业，共5个行业\n    industry_map = {sym: f\"IND_{i // 10}\" for i, sym in enumerate(symbols)}\n\n    config = StrategyConfig(name=\"test_multi_factor\")\n\n    # 测试 1：不做中性化\n    strategy = MultiFactorStrategy(\n        config=config,\n        factors={\"momentum\": (factor_df, 1)},\n        is_st_wide=is_st,\n        n_stocks=10,\n    )\n    result = strategy.run(price_wide)\n    print(f\"✅ 无中性化回测完成 | 形状: {result.shape} | 累计收益: {result['cumulative_return'].iloc[-1]:.2%}\")\n\n    # 测试 2：开启行业中性化\n    strategy2 = MultiFactorStrategy(\n        config=config,\n        factors={\"momentum\": (factor_df, 1)},\n        is_st_wide=is_st,\n        n_stocks=10,\n        neutralize=True,\n        industry_map=industry_map,\n    )\n    result2 = strategy2.run(price_wide)\n    print(f\"✅ 行业中性化回测完成 | 形状: {result2.shape} | 累计收益: {result2['cumulative_return'].iloc[-1]:.2%}\")\n\n    # 测试 3：neutralize=True 但不传 industry_map，应打 warning 而非报错\n    import warnings as _w\n    with _w.catch_warnings(record=True) as caught:\n        _w.simplefilter(\"always\")\n        strategy3 = MultiFactorStrategy(\n            config=config,\n            factors={\"momentum\": (factor_df, 1)},\n            n_stocks=10,\n            neutralize=True,         # 未传 industry_map\n        )\n        result3 = strategy3.run(price_wide)\n    assert any(\"industry_map\" in str(w.message) for w in caught), \"应有 warning 提示缺少 industry_map\"\n    print(f\"✅ 缺少 industry_map warning 正常触发\")\n"}